hyveos_sdk/.gitignore
hyveos_sdk/__init__.py
hyveos_sdk/connection.py
hyveos_sdk/proto-check/script_pb2.py
hyveos_sdk/proto-check/script_pb2.pyi
hyveos_sdk/proto-check/script_pb2_grpc.py
hyveos_sdk/protocol/__init__.py
hyveos_sdk/protocol/script_pb2.py
hyveos_sdk/protocol/script_pb2.pyi
hyveos_sdk/protocol/script_pb2_grpc.py
hyveos_sdk/services/db.py
hyveos_sdk/services/debug.py
hyveos_sdk/services/dht.py
hyveos_sdk/services/discovery.py
hyveos_sdk/services/file_transfer.py
hyveos_sdk/services/gossip_sub.py
hyveos_sdk/services/request_response.py
hyveos_sdk/services/scripting.py
hyveos_sdk/services/stream.py
hyveos_sdk/services/util.py
hyveos_sdk-0.1.1.dist-info/LICENSE.md
hyveos_sdk-0.1.1.dist-info/METADATA
hyveos_sdk-0.1.1.dist-info/WHEEL
hyveos_sdk-0.1.1.dist-info/RECORD
