Metadata-Version: 2.3
Name: hyveos-sdk
Version: 0.1.1
Summary: 
License: MIT
Author: Lukas Altun
Author-email: laltun@student.ethz.ch
Requires-Python: >=3.11,<4.0
Classifier: License :: OSI Approved :: MIT License
Classifier: Programming Language :: Python :: 3
Classifier: Programming Language :: Python :: 3.11
Classifier: Programming Language :: Python :: 3.12
Classifier: Programming Language :: Python :: 3.13
Requires-Dist: aiohttp (>=3.11.11,<4.0.0)
Requires-Dist: grpcio (>=1.69.0,<2.0.0)
Requires-Dist: protobuf (>=5.29.2,<6.0.0)
Requires-Dist: yarl (>=1.18.3,<2.0.0)
